fornax/__init__.py
fornax/api.py
fornax/model.py
fornax/opt.py
fornax/select.py
fornax/version.py
test/__init__.py
test/test_api.py
test/test_base.py
test/test_model.py
test/test_opt.py
test/test_select.py
fornax-0.1.1.dist-info/LICENSE
fornax-0.1.1.dist-info/METADATA
fornax-0.1.1.dist-info/WHEEL
fornax-0.1.1.dist-info/top_level.txt
fornax-0.1.1.dist-info/RECORD
