Metadata-Version: 2.1
Name: fornax
Version: 0.1.1
Summary: Approximate fuzzy subgraph matching in polynomial time
Home-page: UNKNOWN
Author: Daniel Staff
Author-email: daniel.staff@digicatapult.org.uk
License: Apache License 2.0
Platform: UNKNOWN
Classifier: Intended Audience :: Developers
Classifier: Intended Audience :: Science/Research
Classifier: License :: OSI Approved :: Apache Software License
Classifier: Natural Language :: English
Classifier: Topic :: Scientific/Engineering :: Information Analysis
Requires-Python: >=3
Requires-Dist: psycopg2 (>=2.7.4)
Requires-Dist: SQLAlchemy (>=1.2.8)
Requires-Dist: numpy (>-1.14.5)
